azureml/__init__.py
azureml/acft/__init__.py
azureml/acft/contrib/__init__.py
azureml/acft/contrib/hf/__init__.py
azureml/acft/contrib/hf/diffusion/NOTICE
azureml/acft/contrib/hf/diffusion/__init__.py
azureml/acft/contrib/hf/diffusion/base_runner.py
azureml/acft/contrib/hf/diffusion/task_factory.py
azureml/acft/contrib/hf/diffusion/constants/__init__.py
azureml/acft/contrib/hf/diffusion/constants/constants.py
azureml/acft/contrib/hf/diffusion/diffusion_auto/__init__.py
azureml/acft/contrib/hf/diffusion/diffusion_auto/config.py
azureml/acft/contrib/hf/diffusion/diffusion_auto/model.py
azureml/acft/contrib/hf/diffusion/diffusion_auto/scheduler.py
azureml/acft/contrib/hf/diffusion/diffusion_auto/tokenizer.py
azureml/acft/contrib/hf/diffusion/tasks/__init__.py
azureml/acft/contrib/hf/diffusion/tasks/stable_diffusion/__init__.py
azureml/acft/contrib/hf/diffusion/tasks/stable_diffusion/runner.py
azureml/acft/contrib/hf/diffusion/tasks/stable_diffusion/finetune/__init__.py
azureml/acft/contrib/hf/diffusion/tasks/stable_diffusion/finetune/finetune.py
azureml/acft/contrib/hf/diffusion/tasks/stable_diffusion/preprocess/__init__.py
azureml/acft/contrib/hf/diffusion/tasks/stable_diffusion/preprocess/base.py
azureml/acft/contrib/hf/diffusion/tasks/stable_diffusion/preprocess/preprocess_for_finetune.py
azureml/acft/contrib/hf/diffusion/tasks/stable_diffusion/preprocess/preprocess_for_inference.py
azureml/acft/contrib/hf/diffusion/utils/__init__.py
azureml/acft/contrib/hf/diffusion/utils/data_utils.py
azureml/acft/contrib/hf/diffusion/utils/hf_argparser.py
azureml/acft/contrib/hf/diffusion/utils/mlflow_preprocess.py
azureml/acft/contrib/hf/diffusion/utils/mlflow_utils.py
azureml/acft/contrib/hf/diffusion/utils/model_selector_utils.py
azureml/acft/contrib/hf/diffusion/utils/preprocess.py
azureml/acft/contrib/hf/diffusion/utils/validation_utils.py
azureml_acft_contrib_hf_diffusion-47.0.0.data/data/azureml-acft-contrib-hf-diffusion/NOTICE
azureml_acft_contrib_hf_diffusion-47.0.0.dist-info/LICENSE.txt
azureml_acft_contrib_hf_diffusion-47.0.0.dist-info/METADATA
azureml_acft_contrib_hf_diffusion-47.0.0.dist-info/WHEEL
azureml_acft_contrib_hf_diffusion-47.0.0.dist-info/top_level.txt
azureml_acft_contrib_hf_diffusion-47.0.0.dist-info/RECORD
